uvutils/__init__.py
uvutils/image_processing/__init__.py
uvutils/image_processing/resize.py
uvutils/image_processing/utils.py
uvutils-0.0.1.dist-info/METADATA
uvutils-0.0.1.dist-info/WHEEL
uvutils-0.0.1.dist-info/top_level.txt
uvutils-0.0.1.dist-info/RECORD
